tests/builtins/__init__.py
tests/builtins/test_abs.py
tests/builtins/test_all.py
tests/builtins/test_any.py
tests/builtins/test_ascii.py
tests/builtins/test_bin.py
tests/builtins/test_bool.py
tests/builtins/test_bytearray.py
tests/builtins/test_bytes.py
tests/builtins/test_callable.py
tests/builtins/test_chr.py
tests/builtins/test_classmethod.py
tests/builtins/test_compile.py
tests/builtins/test_complex.py
tests/builtins/test_delattr.py
tests/builtins/test_dict.py
tests/builtins/test_dir.py
tests/builtins/test_divmod.py
tests/builtins/test_enumerate.py
tests/builtins/test_eval.py
tests/builtins/test_exec.py
tests/builtins/test_filter.py
tests/builtins/test_float.py
tests/builtins/test_format.py
tests/builtins/test_frozenset.py
tests/builtins/test_getattr.py
tests/builtins/test_globals.py
tests/builtins/test_hasattr.py
tests/builtins/test_hash.py
tests/builtins/test_help.py
tests/builtins/test_hex.py
tests/builtins/test_id.py
tests/builtins/test_import.py
tests/builtins/test_input.py
tests/builtins/test_int.py
tests/builtins/test_isinstance.py
tests/builtins/test_issubclass.py
tests/builtins/test_iter.py
tests/builtins/test_len.py
tests/builtins/test_list.py
tests/builtins/test_locals.py
tests/builtins/test_map.py
tests/builtins/test_max.py
tests/builtins/test_memoryview.py
tests/builtins/test_min.py
tests/builtins/test_next.py
tests/builtins/test_object.py
tests/builtins/test_oct.py
tests/builtins/test_open.py
tests/builtins/test_ord.py
tests/builtins/test_pow.py
tests/builtins/test_print.py
tests/builtins/test_property.py
tests/builtins/test_range.py
tests/builtins/test_repr.py
tests/builtins/test_reversed.py
tests/builtins/test_round.py
tests/builtins/test_set.py
tests/builtins/test_setattr.py
tests/builtins/test_slice.py
tests/builtins/test_sorted.py
tests/builtins/test_staticmethod.py
tests/builtins/test_str.py
tests/builtins/test_sum.py
tests/builtins/test_super.py
tests/builtins/test_tuple.py
voc-0.1.6.dist-info/DESCRIPTION.rst
voc-0.1.6.dist-info/METADATA
voc-0.1.6.dist-info/RECORD
voc-0.1.6.dist-info/WHEEL
voc-0.1.6.dist-info/entry_points.txt
voc-0.1.6.dist-info/metadata.json
voc-0.1.6.dist-info/pbr.json
voc-0.1.6.dist-info/top_level.txt
